<?xml version="1.0" encoding="UTF-8"?>
<config-server xmlns="http://programyourhome.com/config" xmlns:xsi="http://www.w3.org/2001/XMLSchema-instance" xsi:schemaLocation="http://programyourhome.com/config ../xsd/program-your-home-config-server.xsd">
    <activities>
        <activity>
            <name>Watch TV</name>
            <icon>television.png</icon>
            <modules>
                <philips-hue>
                    <light>
                        <toTurnOn>Bank</toTurnOn>
                        <dim>100</dim>
                        <colorMood>relax</colorMood>
                    </light>
                    <light>
                        <toTurnOff>Box</toTurnOff>
                    </light>
                </philips-hue>
                <infra-red>
                    <pyhir>
                        <ir>6</ir>
                    </pyhir>
                </infra-red>
            </modules>
        </activity>
    </activities>
</config-server>
